pytest_cpp/__init__.py
pytest_cpp/boost.py
pytest_cpp/catch2.py
pytest_cpp/error.py
pytest_cpp/facade_abc.py
pytest_cpp/google.py
pytest_cpp/helpers.py
pytest_cpp/plugin.py
pytest_cpp-2.5.0.dist-info/LICENSE
pytest_cpp-2.5.0.dist-info/METADATA
pytest_cpp-2.5.0.dist-info/WHEEL
pytest_cpp-2.5.0.dist-info/entry_points.txt
pytest_cpp-2.5.0.dist-info/top_level.txt
pytest_cpp-2.5.0.dist-info/RECORD
