Metadata-Version: 2.1
Name: pytest-cpp
Version: 2.5.0
Summary: Use pytest's runner to discover and execute C++ tests
Home-page: http://github.com/pytest-dev/pytest-cpp
Author: Bruno Oliveira
Author-email: nicoddemus@gmail.com
License: MIT
Keywords: pytest test unittest
Classifier: Development Status :: 5 - Production/Stable
Classifier: Framework :: Pytest
Classifier: Intended Audience :: Developers
Classifier: License :: OSI Approved :: MIT License
Classifier: Operating System :: OS Independent
Classifier: Programming Language :: Python :: 3
Classifier: Programming Language :: Python :: 3.7
Classifier: Programming Language :: Python :: 3.8
Classifier: Programming Language :: Python :: 3.9
Classifier: Programming Language :: Python :: 3.10
Classifier: Programming Language :: Python :: 3.11
Classifier: Programming Language :: Python :: 3.12
Classifier: Programming Language :: C++
Classifier: Topic :: Software Development :: Quality Assurance
Classifier: Topic :: Software Development :: Testing
Requires-Python: >=3.7
License-File: LICENSE
Requires-Dist: pytest>=7.0
Requires-Dist: colorama
